Metadata-Version: 1.1
Name: caustic.pants
Version: 1.0.4
Summary: Caustic plugin for Pants
Home-page: https://github.com/ashwin153/caustic
Author: Ashwin Madavan
Author-email: ashwin.madavan@gmail.com
License: Apache License, Version 2.0
Platform: UNKNOWN
Classifier: Intended Audience :: Developers
Classifier: License :: OSI Approved :: Apache Software License
Classifier: Operating System :: OS Independent
Classifier: Programming Language :: Python
